ultraheatmap/__init__.py
ultraheatmap/addFeatureToMatrix.py
ultraheatmap/computeMatrix.py
ultraheatmap/computeOrderedMatrix.py
ultraheatmap/mapClosestGenes.py
ultraheatmap/parseTables.py
ultraheatmap/plotHeatMap.py
ultraheatmap/ultraheatmap_tools_list.py
ultraheatmap/configs/computeOrderedMatrix.yaml
ultraheatmap-1.3.0.data/scripts/addFeatureToMatrix
ultraheatmap-1.3.0.data/scripts/computeOrderedMatrix
ultraheatmap-1.3.0.data/scripts/ultraheatmap
ultraheatmap-1.3.0.dist-info/LICENSE
ultraheatmap-1.3.0.dist-info/METADATA
ultraheatmap-1.3.0.dist-info/WHEEL
ultraheatmap-1.3.0.dist-info/top_level.txt
ultraheatmap-1.3.0.dist-info/RECORD
