Metadata-Version: 2.1
Name: ultraheatmap
Version: 1.3.0
Summary: UNKNOWN
Home-page: UNKNOWN
Author: UNKNOWN
Author-email: UNKNOWN
License: MIT
Platform: UNKNOWN
